au_nz_jobs/__init__.py
au_nz_jobs/downloader/__init__.py
au_nz_jobs/downloader/downloader.py
au_nz_jobs/save_jobs/__init__.py
au_nz_jobs/save_jobs/save_jobs.py
au_nz_jobs-0.1.0.dist-info/AUTHORS.md
au_nz_jobs-0.1.0.dist-info/LICENSE
au_nz_jobs-0.1.0.dist-info/METADATA
au_nz_jobs-0.1.0.dist-info/WHEEL
au_nz_jobs-0.1.0.dist-info/top_level.txt
au_nz_jobs-0.1.0.dist-info/RECORD
