Metadata-Version: 2.1
Name: au-nz-jobs
Version: 0.1.0
Summary: A package to download and save jobs in Australian and New Zealand from SEEK.
Home-page: https://github.com/tsy0716/au_nz_jobs
Author: Robert Tu
Author-email: tsy0716@gmail.com
License: GNU General Public License v3
Keywords: au_nz_jobs
Classifier: Development Status :: 2 - Pre-Alpha
Classifier: Intended Audience :: Developers
Classifier: License :: OSI Approved :: GNU General Public License v3 (GPLv3)
Classifier: Natural Language :: English
Classifier: Programming Language :: Python :: 3
Classifier: Programming Language :: Python :: 3.6
Classifier: Programming Language :: Python :: 3.7
Classifier: Programming Language :: Python :: 3.8
Requires-Python: >=3.6
License-File: LICENSE
License-File: AUTHORS.md
